{
    "dataset_description": {
        "BIDSVersion": "1.0.0",
        "License": "This dataset is made available under the Public Domain Dedication and License \nv1.0, whose full text can be found at \nhttp://www.opendatacommons.org/licenses/pddl/1.0/. \nWe hope that all users will follow the ODC Attribution/Share-Alike \nCommunity Norms (http://www.opendatacommons.org/norms/odc-by-sa/); \nin particular, while not legally required, we hope that all users \nof the data will acknowledge the OpenfMRI project and NSF Grant \nOCI-1131441 (R. Poldrack, PI) in any publications.",
        "Name": "Word and object processing",
        "ReferencesAndLinks": "Duncan, K.J., Pattamadilok, C., Knierim, I., Devlin, J.T. (2009). Consistency and variability in functional localisers. Neuroimage, 46(4):1018-26. doi: 10.1016/j.neuroimage.2009.03.014"
    },
    "README": "/Users/greg/code/INCF/BIDS-examples/ds107/README",
    "CHANGES": "/Users/greg/code/INCF/BIDS-examples/ds107/CHANGES",
    "participants": {
        "01": {
            "sessions": {
                "1": {
                    "anat": {
                        "T1w": {
                            "runs": {
                                "1": {
                                    "filename": "/Users/greg/code/INCF/BIDS-examples/ds107/sub-01/anat/sub-01_T1w.nii.gz"
                                }
                            }
                        }
                    },
                    "func": {
                        "onebacktask": {
                            "runs": {
                                "01": {
                                    "filename": "/Users/greg/code/INCF/BIDS-examples/ds107/sub-01/func/sub-01_task-onebacktask_run-01_bold.nii.gz",
                                    "metadata": {
                                        "RepetitionTime": 3.0,
                                        "TaskName": "one-back task"
                                    },
                                    "events": "/Users/greg/code/INCF/BIDS-examples/ds107/sub-01/func/sub-01_task-onebacktask_run-01_events.tsv"
                                },
                                "02": {
                                    "filename": "/Users/greg/code/INCF/BIDS-examples/ds107/sub-01/func/sub-01_task-onebacktask_run-02_bold.nii.gz",
                                    "metadata": {
                                        "RepetitionTime": 3.0,
                                        "TaskName": "one-back task"
                                    },
                                    "events": "/Users/greg/code/INCF/BIDS-examples/ds107/sub-01/func/sub-01_task-onebacktask_run-02_events.tsv"
                                }
                            }
                        }
                    }
                }
            }
        },
        "02": {
            "sessions": {
                "1": {
                    "anat": {
                        "T1w": {
                            "runs": {
                                "1": {
                                    "filename": "/Users/greg/code/INCF/BIDS-examples/ds107/sub-02/anat/sub-02_T1w.nii.gz"
                                }
                            }
                        }
                    },
                    "func": {
                        "onebacktask": {
                            "runs": {
                                "01": {
                                    "filename": "/Users/greg/code/INCF/BIDS-examples/ds107/sub-02/func/sub-02_task-onebacktask_run-01_bold.nii.gz",
                                    "metadata": {
                                        "RepetitionTime": 3.0,
                                        "TaskName": "one-back task"
                                    },
                                    "events": "/Users/greg/code/INCF/BIDS-examples/ds107/sub-02/func/sub-02_task-onebacktask_run-01_events.tsv"
                                },
                                "02": {
                                    "filename": "/Users/greg/code/INCF/BIDS-examples/ds107/sub-02/func/sub-02_task-onebacktask_run-02_bold.nii.gz",
                                    "metadata": {
                                        "RepetitionTime": 3.0,
                                        "TaskName": "one-back task"
                                    },
                                    "events": "/Users/greg/code/INCF/BIDS-examples/ds107/sub-02/func/sub-02_task-onebacktask_run-02_events.tsv"
                                }
                            }
                        }
                    }
                }
            }
        },
        "03": {
            "sessions": {
                "1": {
                    "anat": {
                        "T1w": {
                            "runs": {
                                "1": {
                                    "filename": "/Users/greg/code/INCF/BIDS-examples/ds107/sub-03/anat/sub-03_T1w.nii.gz"
                                }
                            }
                        }
                    },
                    "func": {
                        "onebacktask": {
                            "runs": {
                                "01": {
                                    "filename": "/Users/greg/code/INCF/BIDS-examples/ds107/sub-03/func/sub-03_task-onebacktask_run-01_bold.nii.gz",
                                    "metadata": {
                                        "RepetitionTime": 3.0,
                                        "TaskName": "one-back task"
                                    },
                                    "events": "/Users/greg/code/INCF/BIDS-examples/ds107/sub-03/func/sub-03_task-onebacktask_run-01_events.tsv"
                                },
                                "02": {
                                    "filename": "/Users/greg/code/INCF/BIDS-examples/ds107/sub-03/func/sub-03_task-onebacktask_run-02_bold.nii.gz",
                                    "metadata": {
                                        "RepetitionTime": 3.0,
                                        "TaskName": "one-back task"
                                    },
                                    "events": "/Users/greg/code/INCF/BIDS-examples/ds107/sub-03/func/sub-03_task-onebacktask_run-02_events.tsv"
                                }
                            }
                        }
                    }
                }
            }
        },
        "04": {
            "sessions": {
                "1": {
                    "anat": {
                        "T1w": {
                            "runs": {
                                "1": {
                                    "filename": "/Users/greg/code/INCF/BIDS-examples/ds107/sub-04/anat/sub-04_T1w.nii.gz"
                                }
                            }
                        }
                    },
                    "func": {
                        "onebacktask": {
                            "runs": {
                                "01": {
                                    "filename": "/Users/greg/code/INCF/BIDS-examples/ds107/sub-04/func/sub-04_task-onebacktask_run-01_bold.nii.gz",
                                    "metadata": {
                                        "RepetitionTime": 3.0,
                                        "TaskName": "one-back task"
                                    },
                                    "events": "/Users/greg/code/INCF/BIDS-examples/ds107/sub-04/func/sub-04_task-onebacktask_run-01_events.tsv"
                                },
                                "02": {
                                    "filename": "/Users/greg/code/INCF/BIDS-examples/ds107/sub-04/func/sub-04_task-onebacktask_run-02_bold.nii.gz",
                                    "metadata": {
                                        "RepetitionTime": 3.0,
                                        "TaskName": "one-back task"
                                    },
                                    "events": "/Users/greg/code/INCF/BIDS-examples/ds107/sub-04/func/sub-04_task-onebacktask_run-02_events.tsv"
                                }
                            }
                        }
                    }
                }
            }
        },
        "05": {
            "sessions": {
                "1": {
                    "anat": {
                        "T1w": {
                            "runs": {
                                "1": {
                                    "filename": "/Users/greg/code/INCF/BIDS-examples/ds107/sub-05/anat/sub-05_T1w.nii.gz"
                                }
                            }
                        }
                    },
                    "func": {
                        "onebacktask": {
                            "runs": {
                                "01": {
                                    "filename": "/Users/greg/code/INCF/BIDS-examples/ds107/sub-05/func/sub-05_task-onebacktask_run-01_bold.nii.gz",
                                    "metadata": {
                                        "RepetitionTime": 3.0,
                                        "TaskName": "one-back task"
                                    },
                                    "events": "/Users/greg/code/INCF/BIDS-examples/ds107/sub-05/func/sub-05_task-onebacktask_run-01_events.tsv"
                                },
                                "02": {
                                    "filename": "/Users/greg/code/INCF/BIDS-examples/ds107/sub-05/func/sub-05_task-onebacktask_run-02_bold.nii.gz",
                                    "metadata": {
                                        "RepetitionTime": 3.0,
                                        "TaskName": "one-back task"
                                    },
                                    "events": "/Users/greg/code/INCF/BIDS-examples/ds107/sub-05/func/sub-05_task-onebacktask_run-02_events.tsv"
                                }
                            }
                        }
                    }
                }
            }
        },
        "06": {
            "sessions": {
                "1": {
                    "anat": {
                        "T1w": {
                            "runs": {
                                "1": {
                                    "filename": "/Users/greg/code/INCF/BIDS-examples/ds107/sub-06/anat/sub-06_T1w.nii.gz"
                                }
                            }
                        }
                    },
                    "func": {
                        "onebacktask": {
                            "runs": {
                                "01": {
                                    "filename": "/Users/greg/code/INCF/BIDS-examples/ds107/sub-06/func/sub-06_task-onebacktask_run-01_bold.nii.gz",
                                    "metadata": {
                                        "RepetitionTime": 3.0,
                                        "TaskName": "one-back task"
                                    },
                                    "events": "/Users/greg/code/INCF/BIDS-examples/ds107/sub-06/func/sub-06_task-onebacktask_run-01_events.tsv"
                                },
                                "02": {
                                    "filename": "/Users/greg/code/INCF/BIDS-examples/ds107/sub-06/func/sub-06_task-onebacktask_run-02_bold.nii.gz",
                                    "metadata": {
                                        "RepetitionTime": 3.0,
                                        "TaskName": "one-back task"
                                    },
                                    "events": "/Users/greg/code/INCF/BIDS-examples/ds107/sub-06/func/sub-06_task-onebacktask_run-02_events.tsv"
                                }
                            }
                        }
                    }
                }
            }
        },
        "07": {
            "sessions": {
                "1": {
                    "anat": {
                        "T1w": {
                            "runs": {
                                "1": {
                                    "filename": "/Users/greg/code/INCF/BIDS-examples/ds107/sub-07/anat/sub-07_T1w.nii.gz"
                                }
                            }
                        }
                    },
                    "func": {
                        "onebacktask": {
                            "runs": {
                                "01": {
                                    "filename": "/Users/greg/code/INCF/BIDS-examples/ds107/sub-07/func/sub-07_task-onebacktask_run-01_bold.nii.gz",
                                    "metadata": {
                                        "RepetitionTime": 3.0,
                                        "TaskName": "one-back task"
                                    },
                                    "events": "/Users/greg/code/INCF/BIDS-examples/ds107/sub-07/func/sub-07_task-onebacktask_run-01_events.tsv"
                                },
                                "02": {
                                    "filename": "/Users/greg/code/INCF/BIDS-examples/ds107/sub-07/func/sub-07_task-onebacktask_run-02_bold.nii.gz",
                                    "metadata": {
                                        "RepetitionTime": 3.0,
                                        "TaskName": "one-back task"
                                    },
                                    "events": "/Users/greg/code/INCF/BIDS-examples/ds107/sub-07/func/sub-07_task-onebacktask_run-02_events.tsv"
                                }
                            }
                        }
                    }
                }
            }
        },
        "08": {
            "sessions": {
                "1": {
                    "anat": {
                        "T1w": {
                            "runs": {
                                "1": {
                                    "filename": "/Users/greg/code/INCF/BIDS-examples/ds107/sub-08/anat/sub-08_T1w.nii.gz"
                                }
                            }
                        }
                    },
                    "func": {
                        "onebacktask": {
                            "runs": {
                                "01": {
                                    "filename": "/Users/greg/code/INCF/BIDS-examples/ds107/sub-08/func/sub-08_task-onebacktask_run-01_bold.nii.gz",
                                    "metadata": {
                                        "RepetitionTime": 3.0,
                                        "TaskName": "one-back task"
                                    },
                                    "events": "/Users/greg/code/INCF/BIDS-examples/ds107/sub-08/func/sub-08_task-onebacktask_run-01_events.tsv"
                                },
                                "02": {
                                    "filename": "/Users/greg/code/INCF/BIDS-examples/ds107/sub-08/func/sub-08_task-onebacktask_run-02_bold.nii.gz",
                                    "metadata": {
                                        "RepetitionTime": 3.0,
                                        "TaskName": "one-back task"
                                    },
                                    "events": "/Users/greg/code/INCF/BIDS-examples/ds107/sub-08/func/sub-08_task-onebacktask_run-02_events.tsv"
                                }
                            }
                        }
                    }
                }
            }
        },
        "09": {
            "sessions": {
                "1": {
                    "anat": {
                        "T1w": {
                            "runs": {
                                "1": {
                                    "filename": "/Users/greg/code/INCF/BIDS-examples/ds107/sub-09/anat/sub-09_T1w.nii.gz"
                                }
                            }
                        }
                    },
                    "func": {
                        "onebacktask": {
                            "runs": {
                                "01": {
                                    "filename": "/Users/greg/code/INCF/BIDS-examples/ds107/sub-09/func/sub-09_task-onebacktask_run-01_bold.nii.gz",
                                    "metadata": {
                                        "RepetitionTime": 3.0,
                                        "TaskName": "one-back task"
                                    },
                                    "events": "/Users/greg/code/INCF/BIDS-examples/ds107/sub-09/func/sub-09_task-onebacktask_run-01_events.tsv"
                                },
                                "02": {
                                    "filename": "/Users/greg/code/INCF/BIDS-examples/ds107/sub-09/func/sub-09_task-onebacktask_run-02_bold.nii.gz",
                                    "metadata": {
                                        "RepetitionTime": 3.0,
                                        "TaskName": "one-back task"
                                    },
                                    "events": "/Users/greg/code/INCF/BIDS-examples/ds107/sub-09/func/sub-09_task-onebacktask_run-02_events.tsv"
                                }
                            }
                        }
                    }
                }
            }
        },
        "10": {
            "sessions": {
                "1": {
                    "anat": {
                        "T1w": {
                            "runs": {
                                "1": {
                                    "filename": "/Users/greg/code/INCF/BIDS-examples/ds107/sub-10/anat/sub-10_T1w.nii.gz"
                                }
                            }
                        }
                    },
                    "func": {
                        "onebacktask": {
                            "runs": {
                                "01": {
                                    "filename": "/Users/greg/code/INCF/BIDS-examples/ds107/sub-10/func/sub-10_task-onebacktask_run-01_bold.nii.gz",
                                    "metadata": {
                                        "RepetitionTime": 3.0,
                                        "TaskName": "one-back task"
                                    },
                                    "events": "/Users/greg/code/INCF/BIDS-examples/ds107/sub-10/func/sub-10_task-onebacktask_run-01_events.tsv"
                                },
                                "02": {
                                    "filename": "/Users/greg/code/INCF/BIDS-examples/ds107/sub-10/func/sub-10_task-onebacktask_run-02_bold.nii.gz",
                                    "metadata": {
                                        "RepetitionTime": 3.0,
                                        "TaskName": "one-back task"
                                    },
                                    "events": "/Users/greg/code/INCF/BIDS-examples/ds107/sub-10/func/sub-10_task-onebacktask_run-02_events.tsv"
                                }
                            }
                        }
                    }
                }
            }
        },
        "11": {
            "sessions": {
                "1": {
                    "anat": {
                        "T1w": {
                            "runs": {
                                "1": {
                                    "filename": "/Users/greg/code/INCF/BIDS-examples/ds107/sub-11/anat/sub-11_T1w.nii.gz"
                                }
                            }
                        }
                    },
                    "func": {
                        "onebacktask": {
                            "runs": {
                                "01": {
                                    "filename": "/Users/greg/code/INCF/BIDS-examples/ds107/sub-11/func/sub-11_task-onebacktask_run-01_bold.nii.gz",
                                    "metadata": {
                                        "RepetitionTime": 3.0,
                                        "TaskName": "one-back task"
                                    },
                                    "events": "/Users/greg/code/INCF/BIDS-examples/ds107/sub-11/func/sub-11_task-onebacktask_run-01_events.tsv"
                                },
                                "02": {
                                    "filename": "/Users/greg/code/INCF/BIDS-examples/ds107/sub-11/func/sub-11_task-onebacktask_run-02_bold.nii.gz",
                                    "metadata": {
                                        "RepetitionTime": 3.0,
                                        "TaskName": "one-back task"
                                    },
                                    "events": "/Users/greg/code/INCF/BIDS-examples/ds107/sub-11/func/sub-11_task-onebacktask_run-02_events.tsv"
                                }
                            }
                        }
                    }
                }
            }
        },
        "12": {
            "sessions": {
                "1": {
                    "anat": {
                        "T1w": {
                            "runs": {
                                "1": {
                                    "filename": "/Users/greg/code/INCF/BIDS-examples/ds107/sub-12/anat/sub-12_T1w.nii.gz"
                                }
                            }
                        }
                    },
                    "func": {
                        "onebacktask": {
                            "runs": {
                                "01": {
                                    "filename": "/Users/greg/code/INCF/BIDS-examples/ds107/sub-12/func/sub-12_task-onebacktask_run-01_bold.nii.gz",
                                    "metadata": {
                                        "RepetitionTime": 3.0,
                                        "TaskName": "one-back task"
                                    },
                                    "events": "/Users/greg/code/INCF/BIDS-examples/ds107/sub-12/func/sub-12_task-onebacktask_run-01_events.tsv"
                                },
                                "02": {
                                    "filename": "/Users/greg/code/INCF/BIDS-examples/ds107/sub-12/func/sub-12_task-onebacktask_run-02_bold.nii.gz",
                                    "metadata": {
                                        "RepetitionTime": 3.0,
                                        "TaskName": "one-back task"
                                    },
                                    "events": "/Users/greg/code/INCF/BIDS-examples/ds107/sub-12/func/sub-12_task-onebacktask_run-02_events.tsv"
                                }
                            }
                        }
                    }
                }
            }
        },
        "13": {
            "sessions": {
                "1": {
                    "anat": {
                        "T1w": {
                            "runs": {
                                "1": {
                                    "filename": "/Users/greg/code/INCF/BIDS-examples/ds107/sub-13/anat/sub-13_T1w.nii.gz"
                                }
                            }
                        }
                    },
                    "func": {
                        "onebacktask": {
                            "runs": {
                                "01": {
                                    "filename": "/Users/greg/code/INCF/BIDS-examples/ds107/sub-13/func/sub-13_task-onebacktask_run-01_bold.nii.gz",
                                    "metadata": {
                                        "RepetitionTime": 3.0,
                                        "TaskName": "one-back task"
                                    },
                                    "events": "/Users/greg/code/INCF/BIDS-examples/ds107/sub-13/func/sub-13_task-onebacktask_run-01_events.tsv"
                                },
                                "02": {
                                    "filename": "/Users/greg/code/INCF/BIDS-examples/ds107/sub-13/func/sub-13_task-onebacktask_run-02_bold.nii.gz",
                                    "metadata": {
                                        "RepetitionTime": 3.0,
                                        "TaskName": "one-back task"
                                    },
                                    "events": "/Users/greg/code/INCF/BIDS-examples/ds107/sub-13/func/sub-13_task-onebacktask_run-02_events.tsv"
                                }
                            }
                        }
                    }
                }
            }
        },
        "14": {
            "sessions": {
                "1": {
                    "anat": {
                        "T1w": {
                            "runs": {
                                "1": {
                                    "filename": "/Users/greg/code/INCF/BIDS-examples/ds107/sub-14/anat/sub-14_T1w.nii.gz"
                                }
                            }
                        }
                    },
                    "func": {
                        "onebacktask": {
                            "runs": {
                                "01": {
                                    "filename": "/Users/greg/code/INCF/BIDS-examples/ds107/sub-14/func/sub-14_task-onebacktask_run-01_bold.nii.gz",
                                    "metadata": {
                                        "RepetitionTime": 3.0,
                                        "TaskName": "one-back task"
                                    },
                                    "events": "/Users/greg/code/INCF/BIDS-examples/ds107/sub-14/func/sub-14_task-onebacktask_run-01_events.tsv"
                                },
                                "02": {
                                    "filename": "/Users/greg/code/INCF/BIDS-examples/ds107/sub-14/func/sub-14_task-onebacktask_run-02_bold.nii.gz",
                                    "metadata": {
                                        "RepetitionTime": 3.0,
                                        "TaskName": "one-back task"
                                    },
                                    "events": "/Users/greg/code/INCF/BIDS-examples/ds107/sub-14/func/sub-14_task-onebacktask_run-02_events.tsv"
                                }
                            }
                        }
                    }
                }
            }
        },
        "15": {
            "sessions": {
                "1": {
                    "anat": {
                        "T1w": {
                            "runs": {
                                "1": {
                                    "filename": "/Users/greg/code/INCF/BIDS-examples/ds107/sub-15/anat/sub-15_T1w.nii.gz"
                                }
                            }
                        }
                    },
                    "func": {
                        "onebacktask": {
                            "runs": {
                                "01": {
                                    "filename": "/Users/greg/code/INCF/BIDS-examples/ds107/sub-15/func/sub-15_task-onebacktask_run-01_bold.nii.gz",
                                    "metadata": {
                                        "RepetitionTime": 3.0,
                                        "TaskName": "one-back task"
                                    },
                                    "events": "/Users/greg/code/INCF/BIDS-examples/ds107/sub-15/func/sub-15_task-onebacktask_run-01_events.tsv"
                                },
                                "02": {
                                    "filename": "/Users/greg/code/INCF/BIDS-examples/ds107/sub-15/func/sub-15_task-onebacktask_run-02_bold.nii.gz",
                                    "metadata": {
                                        "RepetitionTime": 3.0,
                                        "TaskName": "one-back task"
                                    },
                                    "events": "/Users/greg/code/INCF/BIDS-examples/ds107/sub-15/func/sub-15_task-onebacktask_run-02_events.tsv"
                                }
                            }
                        }
                    }
                }
            }
        },
        "16": {
            "sessions": {
                "1": {
                    "anat": {
                        "T1w": {
                            "runs": {
                                "1": {
                                    "filename": "/Users/greg/code/INCF/BIDS-examples/ds107/sub-16/anat/sub-16_T1w.nii.gz"
                                }
                            }
                        }
                    },
                    "func": {
                        "onebacktask": {
                            "runs": {
                                "01": {
                                    "filename": "/Users/greg/code/INCF/BIDS-examples/ds107/sub-16/func/sub-16_task-onebacktask_run-01_bold.nii.gz",
                                    "metadata": {
                                        "RepetitionTime": 3.0,
                                        "TaskName": "one-back task"
                                    },
                                    "events": "/Users/greg/code/INCF/BIDS-examples/ds107/sub-16/func/sub-16_task-onebacktask_run-01_events.tsv"
                                },
                                "02": {
                                    "filename": "/Users/greg/code/INCF/BIDS-examples/ds107/sub-16/func/sub-16_task-onebacktask_run-02_bold.nii.gz",
                                    "metadata": {
                                        "RepetitionTime": 3.0,
                                        "TaskName": "one-back task"
                                    },
                                    "events": "/Users/greg/code/INCF/BIDS-examples/ds107/sub-16/func/sub-16_task-onebacktask_run-02_events.tsv"
                                }
                            }
                        }
                    }
                }
            }
        },
        "17": {
            "sessions": {
                "1": {
                    "anat": {
                        "T1w": {
                            "runs": {
                                "1": {
                                    "filename": "/Users/greg/code/INCF/BIDS-examples/ds107/sub-17/anat/sub-17_T1w.nii.gz"
                                }
                            }
                        }
                    },
                    "func": {
                        "onebacktask": {
                            "runs": {
                                "01": {
                                    "filename": "/Users/greg/code/INCF/BIDS-examples/ds107/sub-17/func/sub-17_task-onebacktask_run-01_bold.nii.gz",
                                    "metadata": {
                                        "RepetitionTime": 3.0,
                                        "TaskName": "one-back task"
                                    },
                                    "events": "/Users/greg/code/INCF/BIDS-examples/ds107/sub-17/func/sub-17_task-onebacktask_run-01_events.tsv"
                                },
                                "02": {
                                    "filename": "/Users/greg/code/INCF/BIDS-examples/ds107/sub-17/func/sub-17_task-onebacktask_run-02_bold.nii.gz",
                                    "metadata": {
                                        "RepetitionTime": 3.0,
                                        "TaskName": "one-back task"
                                    },
                                    "events": "/Users/greg/code/INCF/BIDS-examples/ds107/sub-17/func/sub-17_task-onebacktask_run-02_events.tsv"
                                }
                            }
                        }
                    }
                }
            }
        },
        "18": {
            "sessions": {
                "1": {
                    "anat": {
                        "T1w": {
                            "runs": {
                                "1": {
                                    "filename": "/Users/greg/code/INCF/BIDS-examples/ds107/sub-18/anat/sub-18_T1w.nii.gz"
                                }
                            }
                        }
                    },
                    "func": {
                        "onebacktask": {
                            "runs": {
                                "01": {
                                    "filename": "/Users/greg/code/INCF/BIDS-examples/ds107/sub-18/func/sub-18_task-onebacktask_run-01_bold.nii.gz",
                                    "metadata": {
                                        "RepetitionTime": 3.0,
                                        "TaskName": "one-back task"
                                    },
                                    "events": "/Users/greg/code/INCF/BIDS-examples/ds107/sub-18/func/sub-18_task-onebacktask_run-01_events.tsv"
                                },
                                "02": {
                                    "filename": "/Users/greg/code/INCF/BIDS-examples/ds107/sub-18/func/sub-18_task-onebacktask_run-02_bold.nii.gz",
                                    "metadata": {
                                        "RepetitionTime": 3.0,
                                        "TaskName": "one-back task"
                                    },
                                    "events": "/Users/greg/code/INCF/BIDS-examples/ds107/sub-18/func/sub-18_task-onebacktask_run-02_events.tsv"
                                }
                            }
                        }
                    }
                }
            }
        },
        "19": {
            "sessions": {
                "1": {
                    "anat": {
                        "T1w": {
                            "runs": {
                                "1": {
                                    "filename": "/Users/greg/code/INCF/BIDS-examples/ds107/sub-19/anat/sub-19_T1w.nii.gz"
                                }
                            }
                        }
                    },
                    "func": {
                        "onebacktask": {
                            "runs": {
                                "01": {
                                    "filename": "/Users/greg/code/INCF/BIDS-examples/ds107/sub-19/func/sub-19_task-onebacktask_run-01_bold.nii.gz",
                                    "metadata": {
                                        "RepetitionTime": 3.0,
                                        "TaskName": "one-back task"
                                    },
                                    "events": "/Users/greg/code/INCF/BIDS-examples/ds107/sub-19/func/sub-19_task-onebacktask_run-01_events.tsv"
                                },
                                "02": {
                                    "filename": "/Users/greg/code/INCF/BIDS-examples/ds107/sub-19/func/sub-19_task-onebacktask_run-02_bold.nii.gz",
                                    "metadata": {
                                        "RepetitionTime": 3.0,
                                        "TaskName": "one-back task"
                                    },
                                    "events": "/Users/greg/code/INCF/BIDS-examples/ds107/sub-19/func/sub-19_task-onebacktask_run-02_events.tsv"
                                }
                            }
                        }
                    }
                }
            }
        },
        "20": {
            "sessions": {
                "1": {
                    "anat": {
                        "T1w": {
                            "runs": {
                                "1": {
                                    "filename": "/Users/greg/code/INCF/BIDS-examples/ds107/sub-20/anat/sub-20_T1w.nii.gz"
                                }
                            }
                        }
                    },
                    "func": {
                        "onebacktask": {
                            "runs": {
                                "01": {
                                    "filename": "/Users/greg/code/INCF/BIDS-examples/ds107/sub-20/func/sub-20_task-onebacktask_run-01_bold.nii.gz",
                                    "metadata": {
                                        "RepetitionTime": 3.0,
                                        "TaskName": "one-back task"
                                    },
                                    "events": "/Users/greg/code/INCF/BIDS-examples/ds107/sub-20/func/sub-20_task-onebacktask_run-01_events.tsv"
                                },
                                "02": {
                                    "filename": "/Users/greg/code/INCF/BIDS-examples/ds107/sub-20/func/sub-20_task-onebacktask_run-02_bold.nii.gz",
                                    "metadata": {
                                        "RepetitionTime": 3.0,
                                        "TaskName": "one-back task"
                                    },
                                    "events": "/Users/greg/code/INCF/BIDS-examples/ds107/sub-20/func/sub-20_task-onebacktask_run-02_events.tsv"
                                }
                            }
                        }
                    }
                }
            }
        },
        "21": {
            "sessions": {
                "1": {
                    "anat": {
                        "T1w": {
                            "runs": {
                                "1": {
                                    "filename": "/Users/greg/code/INCF/BIDS-examples/ds107/sub-21/anat/sub-21_T1w.nii.gz"
                                }
                            }
                        }
                    },
                    "func": {
                        "onebacktask": {
                            "runs": {
                                "01": {
                                    "filename": "/Users/greg/code/INCF/BIDS-examples/ds107/sub-21/func/sub-21_task-onebacktask_run-01_bold.nii.gz",
                                    "metadata": {
                                        "RepetitionTime": 3.0,
                                        "TaskName": "one-back task"
                                    },
                                    "events": "/Users/greg/code/INCF/BIDS-examples/ds107/sub-21/func/sub-21_task-onebacktask_run-01_events.tsv"
                                },
                                "02": {
                                    "filename": "/Users/greg/code/INCF/BIDS-examples/ds107/sub-21/func/sub-21_task-onebacktask_run-02_bold.nii.gz",
                                    "metadata": {
                                        "RepetitionTime": 3.0,
                                        "TaskName": "one-back task"
                                    },
                                    "events": "/Users/greg/code/INCF/BIDS-examples/ds107/sub-21/func/sub-21_task-onebacktask_run-02_events.tsv"
                                }
                            }
                        }
                    }
                }
            }
        },
        "22": {
            "sessions": {
                "1": {
                    "anat": {
                        "T1w": {
                            "runs": {
                                "1": {
                                    "filename": "/Users/greg/code/INCF/BIDS-examples/ds107/sub-22/anat/sub-22_T1w.nii.gz"
                                }
                            }
                        }
                    },
                    "func": {
                        "onebacktask": {
                            "runs": {
                                "01": {
                                    "filename": "/Users/greg/code/INCF/BIDS-examples/ds107/sub-22/func/sub-22_task-onebacktask_run-01_bold.nii.gz",
                                    "metadata": {
                                        "RepetitionTime": 3.0,
                                        "TaskName": "one-back task"
                                    },
                                    "events": "/Users/greg/code/INCF/BIDS-examples/ds107/sub-22/func/sub-22_task-onebacktask_run-01_events.tsv"
                                },
                                "02": {
                                    "filename": "/Users/greg/code/INCF/BIDS-examples/ds107/sub-22/func/sub-22_task-onebacktask_run-02_bold.nii.gz",
                                    "metadata": {
                                        "RepetitionTime": 3.0,
                                        "TaskName": "one-back task"
                                    },
                                    "events": "/Users/greg/code/INCF/BIDS-examples/ds107/sub-22/func/sub-22_task-onebacktask_run-02_events.tsv"
                                }
                            }
                        }
                    }
                }
            }
        },
        "23": {
            "sessions": {
                "1": {
                    "anat": {
                        "T1w": {
                            "runs": {
                                "1": {
                                    "filename": "/Users/greg/code/INCF/BIDS-examples/ds107/sub-23/anat/sub-23_T1w.nii.gz"
                                }
                            }
                        }
                    },
                    "func": {
                        "onebacktask": {
                            "runs": {
                                "01": {
                                    "filename": "/Users/greg/code/INCF/BIDS-examples/ds107/sub-23/func/sub-23_task-onebacktask_run-01_bold.nii.gz",
                                    "metadata": {
                                        "RepetitionTime": 3.0,
                                        "TaskName": "one-back task"
                                    },
                                    "events": "/Users/greg/code/INCF/BIDS-examples/ds107/sub-23/func/sub-23_task-onebacktask_run-01_events.tsv"
                                },
                                "02": {
                                    "filename": "/Users/greg/code/INCF/BIDS-examples/ds107/sub-23/func/sub-23_task-onebacktask_run-02_bold.nii.gz",
                                    "metadata": {
                                        "RepetitionTime": 3.0,
                                        "TaskName": "one-back task"
                                    },
                                    "events": "/Users/greg/code/INCF/BIDS-examples/ds107/sub-23/func/sub-23_task-onebacktask_run-02_events.tsv"
                                }
                            }
                        }
                    }
                }
            }
        },
        "24": {
            "sessions": {
                "1": {
                    "anat": {
                        "T1w": {
                            "runs": {
                                "1": {
                                    "filename": "/Users/greg/code/INCF/BIDS-examples/ds107/sub-24/anat/sub-24_T1w.nii.gz"
                                }
                            }
                        }
                    },
                    "func": {
                        "onebacktask": {
                            "runs": {
                                "01": {
                                    "filename": "/Users/greg/code/INCF/BIDS-examples/ds107/sub-24/func/sub-24_task-onebacktask_run-01_bold.nii.gz",
                                    "metadata": {
                                        "RepetitionTime": 3.0,
                                        "TaskName": "one-back task"
                                    },
                                    "events": "/Users/greg/code/INCF/BIDS-examples/ds107/sub-24/func/sub-24_task-onebacktask_run-01_events.tsv"
                                },
                                "02": {
                                    "filename": "/Users/greg/code/INCF/BIDS-examples/ds107/sub-24/func/sub-24_task-onebacktask_run-02_bold.nii.gz",
                                    "metadata": {
                                        "RepetitionTime": 3.0,
                                        "TaskName": "one-back task"
                                    },
                                    "events": "/Users/greg/code/INCF/BIDS-examples/ds107/sub-24/func/sub-24_task-onebacktask_run-02_events.tsv"
                                }
                            }
                        }
                    }
                }
            }
        },
        "25": {
            "sessions": {
                "1": {
                    "anat": {
                        "T1w": {
                            "runs": {
                                "1": {
                                    "filename": "/Users/greg/code/INCF/BIDS-examples/ds107/sub-25/anat/sub-25_T1w.nii.gz"
                                }
                            }
                        }
                    },
                    "func": {
                        "onebacktask": {
                            "runs": {
                                "01": {
                                    "filename": "/Users/greg/code/INCF/BIDS-examples/ds107/sub-25/func/sub-25_task-onebacktask_run-01_bold.nii.gz",
                                    "metadata": {
                                        "RepetitionTime": 3.0,
                                        "TaskName": "one-back task"
                                    },
                                    "events": "/Users/greg/code/INCF/BIDS-examples/ds107/sub-25/func/sub-25_task-onebacktask_run-01_events.tsv"
                                },
                                "02": {
                                    "filename": "/Users/greg/code/INCF/BIDS-examples/ds107/sub-25/func/sub-25_task-onebacktask_run-02_bold.nii.gz",
                                    "metadata": {
                                        "RepetitionTime": 3.0,
                                        "TaskName": "one-back task"
                                    },
                                    "events": "/Users/greg/code/INCF/BIDS-examples/ds107/sub-25/func/sub-25_task-onebacktask_run-02_events.tsv"
                                }
                            }
                        }
                    }
                }
            }
        },
        "26": {
            "sessions": {
                "1": {
                    "anat": {
                        "T1w": {
                            "runs": {
                                "1": {
                                    "filename": "/Users/greg/code/INCF/BIDS-examples/ds107/sub-26/anat/sub-26_T1w.nii.gz"
                                }
                            }
                        }
                    },
                    "func": {
                        "onebacktask": {
                            "runs": {
                                "01": {
                                    "filename": "/Users/greg/code/INCF/BIDS-examples/ds107/sub-26/func/sub-26_task-onebacktask_run-01_bold.nii.gz",
                                    "metadata": {
                                        "RepetitionTime": 3.0,
                                        "TaskName": "one-back task"
                                    },
                                    "events": "/Users/greg/code/INCF/BIDS-examples/ds107/sub-26/func/sub-26_task-onebacktask_run-01_events.tsv"
                                },
                                "02": {
                                    "filename": "/Users/greg/code/INCF/BIDS-examples/ds107/sub-26/func/sub-26_task-onebacktask_run-02_bold.nii.gz",
                                    "metadata": {
                                        "RepetitionTime": 3.0,
                                        "TaskName": "one-back task"
                                    },
                                    "events": "/Users/greg/code/INCF/BIDS-examples/ds107/sub-26/func/sub-26_task-onebacktask_run-02_events.tsv"
                                }
                            }
                        }
                    }
                }
            }
        },
        "27": {
            "sessions": {
                "1": {
                    "anat": {
                        "T1w": {
                            "runs": {
                                "1": {
                                    "filename": "/Users/greg/code/INCF/BIDS-examples/ds107/sub-27/anat/sub-27_T1w.nii.gz"
                                }
                            }
                        }
                    },
                    "func": {
                        "onebacktask": {
                            "runs": {
                                "01": {
                                    "filename": "/Users/greg/code/INCF/BIDS-examples/ds107/sub-27/func/sub-27_task-onebacktask_run-01_bold.nii.gz",
                                    "metadata": {
                                        "RepetitionTime": 3.0,
                                        "TaskName": "one-back task"
                                    },
                                    "events": "/Users/greg/code/INCF/BIDS-examples/ds107/sub-27/func/sub-27_task-onebacktask_run-01_events.tsv"
                                },
                                "02": {
                                    "filename": "/Users/greg/code/INCF/BIDS-examples/ds107/sub-27/func/sub-27_task-onebacktask_run-02_bold.nii.gz",
                                    "metadata": {
                                        "RepetitionTime": 3.0,
                                        "TaskName": "one-back task"
                                    },
                                    "events": "/Users/greg/code/INCF/BIDS-examples/ds107/sub-27/func/sub-27_task-onebacktask_run-02_events.tsv"
                                }
                            }
                        }
                    }
                }
            }
        },
        "28": {
            "sessions": {
                "1": {
                    "anat": {
                        "T1w": {
                            "runs": {
                                "1": {
                                    "filename": "/Users/greg/code/INCF/BIDS-examples/ds107/sub-28/anat/sub-28_T1w.nii.gz"
                                }
                            }
                        }
                    },
                    "func": {
                        "onebacktask": {
                            "runs": {
                                "01": {
                                    "filename": "/Users/greg/code/INCF/BIDS-examples/ds107/sub-28/func/sub-28_task-onebacktask_run-01_bold.nii.gz",
                                    "metadata": {
                                        "RepetitionTime": 3.0,
                                        "TaskName": "one-back task"
                                    },
                                    "events": "/Users/greg/code/INCF/BIDS-examples/ds107/sub-28/func/sub-28_task-onebacktask_run-01_events.tsv"
                                },
                                "02": {
                                    "filename": "/Users/greg/code/INCF/BIDS-examples/ds107/sub-28/func/sub-28_task-onebacktask_run-02_bold.nii.gz",
                                    "metadata": {
                                        "RepetitionTime": 3.0,
                                        "TaskName": "one-back task"
                                    },
                                    "events": "/Users/greg/code/INCF/BIDS-examples/ds107/sub-28/func/sub-28_task-onebacktask_run-02_events.tsv"
                                }
                            }
                        }
                    }
                }
            }
        },
        "29": {
            "sessions": {
                "1": {
                    "anat": {
                        "T1w": {
                            "runs": {
                                "1": {
                                    "filename": "/Users/greg/code/INCF/BIDS-examples/ds107/sub-29/anat/sub-29_T1w.nii.gz"
                                }
                            }
                        }
                    },
                    "func": {
                        "onebacktask": {
                            "runs": {
                                "01": {
                                    "filename": "/Users/greg/code/INCF/BIDS-examples/ds107/sub-29/func/sub-29_task-onebacktask_run-01_bold.nii.gz",
                                    "metadata": {
                                        "RepetitionTime": 3.0,
                                        "TaskName": "one-back task"
                                    },
                                    "events": "/Users/greg/code/INCF/BIDS-examples/ds107/sub-29/func/sub-29_task-onebacktask_run-01_events.tsv"
                                },
                                "02": {
                                    "filename": "/Users/greg/code/INCF/BIDS-examples/ds107/sub-29/func/sub-29_task-onebacktask_run-02_bold.nii.gz",
                                    "metadata": {
                                        "RepetitionTime": 3.0,
                                        "TaskName": "one-back task"
                                    },
                                    "events": "/Users/greg/code/INCF/BIDS-examples/ds107/sub-29/func/sub-29_task-onebacktask_run-02_events.tsv"
                                }
                            }
                        }
                    }
                }
            }
        },
        "30": {
            "sessions": {
                "1": {
                    "anat": {
                        "T1w": {
                            "runs": {
                                "1": {
                                    "filename": "/Users/greg/code/INCF/BIDS-examples/ds107/sub-30/anat/sub-30_T1w.nii.gz"
                                }
                            }
                        }
                    },
                    "func": {
                        "onebacktask": {
                            "runs": {
                                "01": {
                                    "filename": "/Users/greg/code/INCF/BIDS-examples/ds107/sub-30/func/sub-30_task-onebacktask_run-01_bold.nii.gz",
                                    "metadata": {
                                        "RepetitionTime": 3.0,
                                        "TaskName": "one-back task"
                                    },
                                    "events": "/Users/greg/code/INCF/BIDS-examples/ds107/sub-30/func/sub-30_task-onebacktask_run-01_events.tsv"
                                },
                                "02": {
                                    "filename": "/Users/greg/code/INCF/BIDS-examples/ds107/sub-30/func/sub-30_task-onebacktask_run-02_bold.nii.gz",
                                    "metadata": {
                                        "RepetitionTime": 3.0,
                                        "TaskName": "one-back task"
                                    },
                                    "events": "/Users/greg/code/INCF/BIDS-examples/ds107/sub-30/func/sub-30_task-onebacktask_run-02_events.tsv"
                                }
                            }
                        }
                    }
                }
            }
        },
        "31": {
            "sessions": {
                "1": {
                    "anat": {
                        "T1w": {
                            "runs": {
                                "1": {
                                    "filename": "/Users/greg/code/INCF/BIDS-examples/ds107/sub-31/anat/sub-31_T1w.nii.gz"
                                }
                            }
                        }
                    },
                    "func": {
                        "onebacktask": {
                            "runs": {
                                "01": {
                                    "filename": "/Users/greg/code/INCF/BIDS-examples/ds107/sub-31/func/sub-31_task-onebacktask_run-01_bold.nii.gz",
                                    "metadata": {
                                        "RepetitionTime": 3.0,
                                        "TaskName": "one-back task"
                                    },
                                    "events": "/Users/greg/code/INCF/BIDS-examples/ds107/sub-31/func/sub-31_task-onebacktask_run-01_events.tsv"
                                },
                                "02": {
                                    "filename": "/Users/greg/code/INCF/BIDS-examples/ds107/sub-31/func/sub-31_task-onebacktask_run-02_bold.nii.gz",
                                    "metadata": {
                                        "RepetitionTime": 3.0,
                                        "TaskName": "one-back task"
                                    },
                                    "events": "/Users/greg/code/INCF/BIDS-examples/ds107/sub-31/func/sub-31_task-onebacktask_run-02_events.tsv"
                                }
                            }
                        }
                    }
                }
            }
        },
        "32": {
            "sessions": {
                "1": {
                    "anat": {
                        "T1w": {
                            "runs": {
                                "1": {
                                    "filename": "/Users/greg/code/INCF/BIDS-examples/ds107/sub-32/anat/sub-32_T1w.nii.gz"
                                }
                            }
                        }
                    },
                    "func": {
                        "onebacktask": {
                            "runs": {
                                "01": {
                                    "filename": "/Users/greg/code/INCF/BIDS-examples/ds107/sub-32/func/sub-32_task-onebacktask_run-01_bold.nii.gz",
                                    "metadata": {
                                        "RepetitionTime": 3.0,
                                        "TaskName": "one-back task"
                                    },
                                    "events": "/Users/greg/code/INCF/BIDS-examples/ds107/sub-32/func/sub-32_task-onebacktask_run-01_events.tsv"
                                },
                                "02": {
                                    "filename": "/Users/greg/code/INCF/BIDS-examples/ds107/sub-32/func/sub-32_task-onebacktask_run-02_bold.nii.gz",
                                    "metadata": {
                                        "RepetitionTime": 3.0,
                                        "TaskName": "one-back task"
                                    },
                                    "events": "/Users/greg/code/INCF/BIDS-examples/ds107/sub-32/func/sub-32_task-onebacktask_run-02_events.tsv"
                                }
                            }
                        }
                    }
                }
            }
        },
        "33": {
            "sessions": {
                "1": {
                    "anat": {
                        "T1w": {
                            "runs": {
                                "1": {
                                    "filename": "/Users/greg/code/INCF/BIDS-examples/ds107/sub-33/anat/sub-33_T1w.nii.gz"
                                }
                            }
                        }
                    },
                    "func": {
                        "onebacktask": {
                            "runs": {
                                "01": {
                                    "filename": "/Users/greg/code/INCF/BIDS-examples/ds107/sub-33/func/sub-33_task-onebacktask_run-01_bold.nii.gz",
                                    "metadata": {
                                        "RepetitionTime": 3.0,
                                        "TaskName": "one-back task"
                                    },
                                    "events": "/Users/greg/code/INCF/BIDS-examples/ds107/sub-33/func/sub-33_task-onebacktask_run-01_events.tsv"
                                },
                                "02": {
                                    "filename": "/Users/greg/code/INCF/BIDS-examples/ds107/sub-33/func/sub-33_task-onebacktask_run-02_bold.nii.gz",
                                    "metadata": {
                                        "RepetitionTime": 3.0,
                                        "TaskName": "one-back task"
                                    },
                                    "events": "/Users/greg/code/INCF/BIDS-examples/ds107/sub-33/func/sub-33_task-onebacktask_run-02_events.tsv"
                                }
                            }
                        }
                    }
                }
            }
        },
        "34": {
            "sessions": {
                "1": {
                    "anat": {
                        "T1w": {
                            "runs": {
                                "1": {
                                    "filename": "/Users/greg/code/INCF/BIDS-examples/ds107/sub-34/anat/sub-34_T1w.nii.gz"
                                }
                            }
                        }
                    },
                    "func": {
                        "onebacktask": {
                            "runs": {
                                "01": {
                                    "filename": "/Users/greg/code/INCF/BIDS-examples/ds107/sub-34/func/sub-34_task-onebacktask_run-01_bold.nii.gz",
                                    "metadata": {
                                        "RepetitionTime": 3.0,
                                        "TaskName": "one-back task"
                                    },
                                    "events": "/Users/greg/code/INCF/BIDS-examples/ds107/sub-34/func/sub-34_task-onebacktask_run-01_events.tsv"
                                },
                                "02": {
                                    "filename": "/Users/greg/code/INCF/BIDS-examples/ds107/sub-34/func/sub-34_task-onebacktask_run-02_bold.nii.gz",
                                    "metadata": {
                                        "RepetitionTime": 3.0,
                                        "TaskName": "one-back task"
                                    },
                                    "events": "/Users/greg/code/INCF/BIDS-examples/ds107/sub-34/func/sub-34_task-onebacktask_run-02_events.tsv"
                                }
                            }
                        }
                    }
                }
            }
        },
        "35": {
            "sessions": {
                "1": {
                    "anat": {
                        "T1w": {
                            "runs": {
                                "1": {
                                    "filename": "/Users/greg/code/INCF/BIDS-examples/ds107/sub-35/anat/sub-35_T1w.nii.gz"
                                }
                            }
                        }
                    },
                    "func": {
                        "onebacktask": {
                            "runs": {
                                "01": {
                                    "filename": "/Users/greg/code/INCF/BIDS-examples/ds107/sub-35/func/sub-35_task-onebacktask_run-01_bold.nii.gz",
                                    "metadata": {
                                        "RepetitionTime": 3.0,
                                        "TaskName": "one-back task"
                                    },
                                    "events": "/Users/greg/code/INCF/BIDS-examples/ds107/sub-35/func/sub-35_task-onebacktask_run-01_events.tsv"
                                },
                                "02": {
                                    "filename": "/Users/greg/code/INCF/BIDS-examples/ds107/sub-35/func/sub-35_task-onebacktask_run-02_bold.nii.gz",
                                    "metadata": {
                                        "RepetitionTime": 3.0,
                                        "TaskName": "one-back task"
                                    },
                                    "events": "/Users/greg/code/INCF/BIDS-examples/ds107/sub-35/func/sub-35_task-onebacktask_run-02_events.tsv"
                                }
                            }
                        }
                    }
                }
            }
        },
        "36": {
            "sessions": {
                "1": {
                    "anat": {
                        "T1w": {
                            "runs": {
                                "1": {
                                    "filename": "/Users/greg/code/INCF/BIDS-examples/ds107/sub-36/anat/sub-36_T1w.nii.gz"
                                }
                            }
                        }
                    },
                    "func": {
                        "onebacktask": {
                            "runs": {
                                "01": {
                                    "filename": "/Users/greg/code/INCF/BIDS-examples/ds107/sub-36/func/sub-36_task-onebacktask_run-01_bold.nii.gz",
                                    "metadata": {
                                        "RepetitionTime": 3.0,
                                        "TaskName": "one-back task"
                                    },
                                    "events": "/Users/greg/code/INCF/BIDS-examples/ds107/sub-36/func/sub-36_task-onebacktask_run-01_events.tsv"
                                },
                                "02": {
                                    "filename": "/Users/greg/code/INCF/BIDS-examples/ds107/sub-36/func/sub-36_task-onebacktask_run-02_bold.nii.gz",
                                    "metadata": {
                                        "RepetitionTime": 3.0,
                                        "TaskName": "one-back task"
                                    },
                                    "events": "/Users/greg/code/INCF/BIDS-examples/ds107/sub-36/func/sub-36_task-onebacktask_run-02_events.tsv"
                                }
                            }
                        }
                    }
                }
            }
        },
        "37": {
            "sessions": {
                "1": {
                    "anat": {
                        "T1w": {
                            "runs": {
                                "1": {
                                    "filename": "/Users/greg/code/INCF/BIDS-examples/ds107/sub-37/anat/sub-37_T1w.nii.gz"
                                }
                            }
                        }
                    },
                    "func": {
                        "onebacktask": {
                            "runs": {
                                "01": {
                                    "filename": "/Users/greg/code/INCF/BIDS-examples/ds107/sub-37/func/sub-37_task-onebacktask_run-01_bold.nii.gz",
                                    "metadata": {
                                        "RepetitionTime": 3.0,
                                        "TaskName": "one-back task"
                                    },
                                    "events": "/Users/greg/code/INCF/BIDS-examples/ds107/sub-37/func/sub-37_task-onebacktask_run-01_events.tsv"
                                },
                                "02": {
                                    "filename": "/Users/greg/code/INCF/BIDS-examples/ds107/sub-37/func/sub-37_task-onebacktask_run-02_bold.nii.gz",
                                    "metadata": {
                                        "RepetitionTime": 3.0,
                                        "TaskName": "one-back task"
                                    },
                                    "events": "/Users/greg/code/INCF/BIDS-examples/ds107/sub-37/func/sub-37_task-onebacktask_run-02_events.tsv"
                                }
                            }
                        }
                    }
                }
            }
        },
        "38": {
            "sessions": {
                "1": {
                    "anat": {
                        "T1w": {
                            "runs": {
                                "1": {
                                    "filename": "/Users/greg/code/INCF/BIDS-examples/ds107/sub-38/anat/sub-38_T1w.nii.gz"
                                }
                            }
                        }
                    },
                    "func": {
                        "onebacktask": {
                            "runs": {
                                "01": {
                                    "filename": "/Users/greg/code/INCF/BIDS-examples/ds107/sub-38/func/sub-38_task-onebacktask_run-01_bold.nii.gz",
                                    "metadata": {
                                        "RepetitionTime": 3.0,
                                        "TaskName": "one-back task"
                                    },
                                    "events": "/Users/greg/code/INCF/BIDS-examples/ds107/sub-38/func/sub-38_task-onebacktask_run-01_events.tsv"
                                },
                                "02": {
                                    "filename": "/Users/greg/code/INCF/BIDS-examples/ds107/sub-38/func/sub-38_task-onebacktask_run-02_bold.nii.gz",
                                    "metadata": {
                                        "RepetitionTime": 3.0,
                                        "TaskName": "one-back task"
                                    },
                                    "events": "/Users/greg/code/INCF/BIDS-examples/ds107/sub-38/func/sub-38_task-onebacktask_run-02_events.tsv"
                                }
                            }
                        }
                    }
                }
            }
        },
        "39": {
            "sessions": {
                "1": {
                    "anat": {
                        "T1w": {
                            "runs": {
                                "1": {
                                    "filename": "/Users/greg/code/INCF/BIDS-examples/ds107/sub-39/anat/sub-39_T1w.nii.gz"
                                }
                            }
                        }
                    },
                    "func": {
                        "onebacktask": {
                            "runs": {
                                "01": {
                                    "filename": "/Users/greg/code/INCF/BIDS-examples/ds107/sub-39/func/sub-39_task-onebacktask_run-01_bold.nii.gz",
                                    "metadata": {
                                        "RepetitionTime": 3.0,
                                        "TaskName": "one-back task"
                                    },
                                    "events": "/Users/greg/code/INCF/BIDS-examples/ds107/sub-39/func/sub-39_task-onebacktask_run-01_events.tsv"
                                },
                                "02": {
                                    "filename": "/Users/greg/code/INCF/BIDS-examples/ds107/sub-39/func/sub-39_task-onebacktask_run-02_bold.nii.gz",
                                    "metadata": {
                                        "RepetitionTime": 3.0,
                                        "TaskName": "one-back task"
                                    },
                                    "events": "/Users/greg/code/INCF/BIDS-examples/ds107/sub-39/func/sub-39_task-onebacktask_run-02_events.tsv"
                                }
                            }
                        }
                    }
                }
            }
        },
        "40": {
            "sessions": {
                "1": {
                    "anat": {
                        "T1w": {
                            "runs": {
                                "1": {
                                    "filename": "/Users/greg/code/INCF/BIDS-examples/ds107/sub-40/anat/sub-40_T1w.nii.gz"
                                }
                            }
                        }
                    },
                    "func": {
                        "onebacktask": {
                            "runs": {
                                "01": {
                                    "filename": "/Users/greg/code/INCF/BIDS-examples/ds107/sub-40/func/sub-40_task-onebacktask_run-01_bold.nii.gz",
                                    "metadata": {
                                        "RepetitionTime": 3.0,
                                        "TaskName": "one-back task"
                                    },
                                    "events": "/Users/greg/code/INCF/BIDS-examples/ds107/sub-40/func/sub-40_task-onebacktask_run-01_events.tsv"
                                },
                                "02": {
                                    "filename": "/Users/greg/code/INCF/BIDS-examples/ds107/sub-40/func/sub-40_task-onebacktask_run-02_bold.nii.gz",
                                    "metadata": {
                                        "RepetitionTime": 3.0,
                                        "TaskName": "one-back task"
                                    },
                                    "events": "/Users/greg/code/INCF/BIDS-examples/ds107/sub-40/func/sub-40_task-onebacktask_run-02_events.tsv"
                                }
                            }
                        }
                    }
                }
            }
        },
        "41": {
            "sessions": {
                "1": {
                    "anat": {
                        "T1w": {
                            "runs": {
                                "1": {
                                    "filename": "/Users/greg/code/INCF/BIDS-examples/ds107/sub-41/anat/sub-41_T1w.nii.gz"
                                }
                            }
                        }
                    },
                    "func": {
                        "onebacktask": {
                            "runs": {
                                "01": {
                                    "filename": "/Users/greg/code/INCF/BIDS-examples/ds107/sub-41/func/sub-41_task-onebacktask_run-01_bold.nii.gz",
                                    "metadata": {
                                        "RepetitionTime": 3.0,
                                        "TaskName": "one-back task"
                                    },
                                    "events": "/Users/greg/code/INCF/BIDS-examples/ds107/sub-41/func/sub-41_task-onebacktask_run-01_events.tsv"
                                },
                                "02": {
                                    "filename": "/Users/greg/code/INCF/BIDS-examples/ds107/sub-41/func/sub-41_task-onebacktask_run-02_bold.nii.gz",
                                    "metadata": {
                                        "RepetitionTime": 3.0,
                                        "TaskName": "one-back task"
                                    },
                                    "events": "/Users/greg/code/INCF/BIDS-examples/ds107/sub-41/func/sub-41_task-onebacktask_run-02_events.tsv"
                                }
                            }
                        }
                    }
                }
            }
        },
        "42": {
            "sessions": {
                "1": {
                    "anat": {
                        "T1w": {
                            "runs": {
                                "1": {
                                    "filename": "/Users/greg/code/INCF/BIDS-examples/ds107/sub-42/anat/sub-42_T1w.nii.gz"
                                }
                            }
                        }
                    },
                    "func": {
                        "onebacktask": {
                            "runs": {
                                "01": {
                                    "filename": "/Users/greg/code/INCF/BIDS-examples/ds107/sub-42/func/sub-42_task-onebacktask_run-01_bold.nii.gz",
                                    "metadata": {
                                        "RepetitionTime": 3.0,
                                        "TaskName": "one-back task"
                                    },
                                    "events": "/Users/greg/code/INCF/BIDS-examples/ds107/sub-42/func/sub-42_task-onebacktask_run-01_events.tsv"
                                },
                                "02": {
                                    "filename": "/Users/greg/code/INCF/BIDS-examples/ds107/sub-42/func/sub-42_task-onebacktask_run-02_bold.nii.gz",
                                    "metadata": {
                                        "RepetitionTime": 3.0,
                                        "TaskName": "one-back task"
                                    },
                                    "events": "/Users/greg/code/INCF/BIDS-examples/ds107/sub-42/func/sub-42_task-onebacktask_run-02_events.tsv"
                                }
                            }
                        }
                    }
                }
            }
        },
        "43": {
            "sessions": {
                "1": {
                    "anat": {
                        "T1w": {
                            "runs": {
                                "1": {
                                    "filename": "/Users/greg/code/INCF/BIDS-examples/ds107/sub-43/anat/sub-43_T1w.nii.gz"
                                }
                            }
                        }
                    },
                    "func": {
                        "onebacktask": {
                            "runs": {
                                "01": {
                                    "filename": "/Users/greg/code/INCF/BIDS-examples/ds107/sub-43/func/sub-43_task-onebacktask_run-01_bold.nii.gz",
                                    "metadata": {
                                        "RepetitionTime": 3.0,
                                        "TaskName": "one-back task"
                                    },
                                    "events": "/Users/greg/code/INCF/BIDS-examples/ds107/sub-43/func/sub-43_task-onebacktask_run-01_events.tsv"
                                },
                                "02": {
                                    "filename": "/Users/greg/code/INCF/BIDS-examples/ds107/sub-43/func/sub-43_task-onebacktask_run-02_bold.nii.gz",
                                    "metadata": {
                                        "RepetitionTime": 3.0,
                                        "TaskName": "one-back task"
                                    },
                                    "events": "/Users/greg/code/INCF/BIDS-examples/ds107/sub-43/func/sub-43_task-onebacktask_run-02_events.tsv"
                                }
                            }
                        }
                    }
                }
            }
        },
        "44": {
            "sessions": {
                "1": {
                    "anat": {
                        "T1w": {
                            "runs": {
                                "1": {
                                    "filename": "/Users/greg/code/INCF/BIDS-examples/ds107/sub-44/anat/sub-44_T1w.nii.gz"
                                }
                            }
                        }
                    },
                    "func": {
                        "onebacktask": {
                            "runs": {
                                "01": {
                                    "filename": "/Users/greg/code/INCF/BIDS-examples/ds107/sub-44/func/sub-44_task-onebacktask_run-01_bold.nii.gz",
                                    "metadata": {
                                        "RepetitionTime": 3.0,
                                        "TaskName": "one-back task"
                                    },
                                    "events": "/Users/greg/code/INCF/BIDS-examples/ds107/sub-44/func/sub-44_task-onebacktask_run-01_events.tsv"
                                },
                                "02": {
                                    "filename": "/Users/greg/code/INCF/BIDS-examples/ds107/sub-44/func/sub-44_task-onebacktask_run-02_bold.nii.gz",
                                    "metadata": {
                                        "RepetitionTime": 3.0,
                                        "TaskName": "one-back task"
                                    },
                                    "events": "/Users/greg/code/INCF/BIDS-examples/ds107/sub-44/func/sub-44_task-onebacktask_run-02_events.tsv"
                                }
                            }
                        }
                    }
                }
            }
        },
        "45": {
            "sessions": {
                "1": {
                    "anat": {
                        "T1w": {
                            "runs": {
                                "1": {
                                    "filename": "/Users/greg/code/INCF/BIDS-examples/ds107/sub-45/anat/sub-45_T1w.nii.gz"
                                }
                            }
                        }
                    },
                    "func": {
                        "onebacktask": {
                            "runs": {
                                "01": {
                                    "filename": "/Users/greg/code/INCF/BIDS-examples/ds107/sub-45/func/sub-45_task-onebacktask_run-01_bold.nii.gz",
                                    "metadata": {
                                        "RepetitionTime": 3.0,
                                        "TaskName": "one-back task"
                                    },
                                    "events": "/Users/greg/code/INCF/BIDS-examples/ds107/sub-45/func/sub-45_task-onebacktask_run-01_events.tsv"
                                },
                                "02": {
                                    "filename": "/Users/greg/code/INCF/BIDS-examples/ds107/sub-45/func/sub-45_task-onebacktask_run-02_bold.nii.gz",
                                    "metadata": {
                                        "RepetitionTime": 3.0,
                                        "TaskName": "one-back task"
                                    },
                                    "events": "/Users/greg/code/INCF/BIDS-examples/ds107/sub-45/func/sub-45_task-onebacktask_run-02_events.tsv"
                                }
                            }
                        }
                    }
                }
            }
        },
        "46": {
            "sessions": {
                "1": {
                    "anat": {
                        "T1w": {
                            "runs": {
                                "1": {
                                    "filename": "/Users/greg/code/INCF/BIDS-examples/ds107/sub-46/anat/sub-46_T1w.nii.gz"
                                }
                            }
                        }
                    },
                    "func": {
                        "onebacktask": {
                            "runs": {
                                "01": {
                                    "filename": "/Users/greg/code/INCF/BIDS-examples/ds107/sub-46/func/sub-46_task-onebacktask_run-01_bold.nii.gz",
                                    "metadata": {
                                        "RepetitionTime": 3.0,
                                        "TaskName": "one-back task"
                                    },
                                    "events": "/Users/greg/code/INCF/BIDS-examples/ds107/sub-46/func/sub-46_task-onebacktask_run-01_events.tsv"
                                },
                                "02": {
                                    "filename": "/Users/greg/code/INCF/BIDS-examples/ds107/sub-46/func/sub-46_task-onebacktask_run-02_bold.nii.gz",
                                    "metadata": {
                                        "RepetitionTime": 3.0,
                                        "TaskName": "one-back task"
                                    },
                                    "events": "/Users/greg/code/INCF/BIDS-examples/ds107/sub-46/func/sub-46_task-onebacktask_run-02_events.tsv"
                                }
                            }
                        }
                    }
                }
            }
        },
        "47": {
            "sessions": {
                "1": {
                    "anat": {
                        "T1w": {
                            "runs": {
                                "1": {
                                    "filename": "/Users/greg/code/INCF/BIDS-examples/ds107/sub-47/anat/sub-47_T1w.nii.gz"
                                }
                            }
                        }
                    },
                    "func": {
                        "onebacktask": {
                            "runs": {
                                "01": {
                                    "filename": "/Users/greg/code/INCF/BIDS-examples/ds107/sub-47/func/sub-47_task-onebacktask_run-01_bold.nii.gz",
                                    "metadata": {
                                        "RepetitionTime": 3.0,
                                        "TaskName": "one-back task"
                                    },
                                    "events": "/Users/greg/code/INCF/BIDS-examples/ds107/sub-47/func/sub-47_task-onebacktask_run-01_events.tsv"
                                },
                                "02": {
                                    "filename": "/Users/greg/code/INCF/BIDS-examples/ds107/sub-47/func/sub-47_task-onebacktask_run-02_bold.nii.gz",
                                    "metadata": {
                                        "RepetitionTime": 3.0,
                                        "TaskName": "one-back task"
                                    },
                                    "events": "/Users/greg/code/INCF/BIDS-examples/ds107/sub-47/func/sub-47_task-onebacktask_run-02_events.tsv"
                                }
                            }
                        }
                    }
                }
            }
        },
        "48": {
            "sessions": {
                "1": {
                    "anat": {
                        "T1w": {
                            "runs": {
                                "1": {
                                    "filename": "/Users/greg/code/INCF/BIDS-examples/ds107/sub-48/anat/sub-48_T1w.nii.gz"
                                }
                            }
                        }
                    },
                    "func": {
                        "onebacktask": {
                            "runs": {
                                "01": {
                                    "filename": "/Users/greg/code/INCF/BIDS-examples/ds107/sub-48/func/sub-48_task-onebacktask_run-01_bold.nii.gz",
                                    "metadata": {
                                        "RepetitionTime": 3.0,
                                        "TaskName": "one-back task"
                                    },
                                    "events": "/Users/greg/code/INCF/BIDS-examples/ds107/sub-48/func/sub-48_task-onebacktask_run-01_events.tsv"
                                },
                                "02": {
                                    "filename": "/Users/greg/code/INCF/BIDS-examples/ds107/sub-48/func/sub-48_task-onebacktask_run-02_bold.nii.gz",
                                    "metadata": {
                                        "RepetitionTime": 3.0,
                                        "TaskName": "one-back task"
                                    },
                                    "events": "/Users/greg/code/INCF/BIDS-examples/ds107/sub-48/func/sub-48_task-onebacktask_run-02_events.tsv"
                                }
                            }
                        }
                    }
                }
            }
        },
        "49": {
            "sessions": {
                "1": {
                    "anat": {
                        "T1w": {
                            "runs": {
                                "1": {
                                    "filename": "/Users/greg/code/INCF/BIDS-examples/ds107/sub-49/anat/sub-49_T1w.nii.gz"
                                }
                            }
                        }
                    },
                    "func": {
                        "onebacktask": {
                            "runs": {
                                "01": {
                                    "filename": "/Users/greg/code/INCF/BIDS-examples/ds107/sub-49/func/sub-49_task-onebacktask_run-01_bold.nii.gz",
                                    "metadata": {
                                        "RepetitionTime": 3.0,
                                        "TaskName": "one-back task"
                                    },
                                    "events": "/Users/greg/code/INCF/BIDS-examples/ds107/sub-49/func/sub-49_task-onebacktask_run-01_events.tsv"
                                },
                                "02": {
                                    "filename": "/Users/greg/code/INCF/BIDS-examples/ds107/sub-49/func/sub-49_task-onebacktask_run-02_bold.nii.gz",
                                    "metadata": {
                                        "RepetitionTime": 3.0,
                                        "TaskName": "one-back task"
                                    },
                                    "events": "/Users/greg/code/INCF/BIDS-examples/ds107/sub-49/func/sub-49_task-onebacktask_run-02_events.tsv"
                                }
                            }
                        }
                    }
                }
            }
        }
    }
}